django_cache_url/__init__.py
django_cache_url-3.3.0.dist-info/AUTHORS.rst
django_cache_url-3.3.0.dist-info/LICENSE
django_cache_url-3.3.0.dist-info/METADATA
django_cache_url-3.3.0.dist-info/WHEEL
django_cache_url-3.3.0.dist-info/top_level.txt
django_cache_url-3.3.0.dist-info/RECORD
